pyactor/__init__.py
pyactor/context.py
pyactor/exceptions.py
pyactor/proxy.py
pyactor/rabbitserver.py
pyactor/rpcserver.py
pyactor/util.py
pyactor/green_thread/__init__.py
pyactor/green_thread/actor.py
pyactor/green_thread/channel.py
pyactor/green_thread/future.py
pyactor/green_thread/intervals.py
pyactor/green_thread/parallels.py
pyactor/green_thread/rpcactor.py
pyactor/thread/__init__.py
pyactor/thread/actor.py
pyactor/thread/channel.py
pyactor/thread/future.py
pyactor/thread/intervals.py
pyactor/thread/parallels.py
pyactor/thread/rpcactor.py
tests/other/__init__.py
tests/other/ffstrss.py
tests/other/pingpong.py
tests/other/r-ringtest.py
tests/other/ringtest.py
tests/other/rping.py
tests/other/rpong.py
tests/other/stress.py
tests/other/stress_server.py
tests/unit/__init__.py
tests/unit/run_tests.py
tests/unit/gevent/__init__.py
tests/unit/gevent/tests.py
tests/unit/gevent/tests_remote.py
tests/unit/thread/__init__.py
tests/unit/thread/tests.py
tests/unit/thread/tests_remote.py
pyactor-2.0.1.dist-info/LICENSE.txt
pyactor-2.0.1.dist-info/METADATA
pyactor-2.0.1.dist-info/WHEEL
pyactor-2.0.1.dist-info/top_level.txt
pyactor-2.0.1.dist-info/RECORD
