Metadata-Version: 2.1
Name: pyactor
Version: 2.0.1
Summary: The minimalistic Python Actor middleware
Home-page: https://github.com/pedrotgn/pyactor
Author: Pedro Garcia Lopez & Daniel Barcelona Pons
Author-email: pedro.garcia@urv.cat, daniel.barcelona@urv.cat
License: GNU
Platform: UNKNOWN
Classifier: Development Status :: 5 - Production/Stable
Classifier: Intended Audience :: Developers
Classifier: Topic :: Software Development :: Libraries
Classifier: License :: OSI Approved :: GNU Lesser General Public License v3 (LGPLv3)
Classifier: Programming Language :: Python :: 3
Classifier: Programming Language :: Python :: 3.7
Requires-Dist: gevent (==1.4.0)
